textwatermark/__init__.py
textwatermark/cmdline.py
textwatermark/common.py
textwatermark/config/__init__.py
textwatermark/config/settings.yml
textwatermark/conversion.py
textwatermark/defines.py
textwatermark/main.py
textwatermark/py.typed
textwatermark/template.py
textwatermark/template_type.py
textwatermark/templates/__init__.py
textwatermark/templates/binary_representation.py
textwatermark/templates/combining_chars.py
textwatermark/templates/font_color.py
textwatermark/templates/font_float.py
textwatermark/templates/font_size.py
textwatermark/templates/font_style.py
textwatermark/templates/font_weight.py
textwatermark/templates/homograph_chinese.py
textwatermark/templates/homograph_letters.py
textwatermark/templates/homograph_numbers.py
textwatermark/templates/homograph_punctuations.py
textwatermark/templates/html_empty_tags.py
textwatermark/templates/invisible_chars.py
textwatermark/templates/space_chars.py
textwatermark/templates/whitespace_chars.py
textwatermark/version.py
textwatermark-0.3.2.dist-info/LICENSE
textwatermark-0.3.2.dist-info/METADATA
textwatermark-0.3.2.dist-info/WHEEL
textwatermark-0.3.2.dist-info/entry_points.txt
textwatermark-0.3.2.dist-info/RECORD
