Metadata-Version: 2.1
Name: textwatermark
Version: 0.3.2
Summary: A watermark library for text.
Home-page: https://textwatermark.jd.army/
License: Apache
Keywords: watermark,text,blind
Author: Monyer
Author-email: monyer@126.com
Requires-Python: >=3.10,<4.0
Classifier: Development Status :: 4 - Beta
Classifier: Environment :: Console
Classifier: Environment :: Plugins
Classifier: Framework :: Pytest
Classifier: Framework :: tox
Classifier: Intended Audience :: Developers
Classifier: Intended Audience :: Information Technology
Classifier: License :: OSI Approved :: Apache Software License
Classifier: License :: Other/Proprietary License
Classifier: Natural Language :: Chinese (Simplified)
Classifier: Natural Language :: English
Classifier: Operating System :: OS Independent
Classifier: Programming Language :: Python :: 3
Classifier: Programming Language :: Python :: 3.10
Classifier: Programming Language :: Python :: 3.11
Classifier: Programming Language :: Python :: 3.10
Classifier: Topic :: Communications :: File Sharing
Classifier: Topic :: Scientific/Engineering :: Information Analysis
Classifier: Topic :: Security
Classifier: Topic :: Text Processing
Requires-Dist: bitstring (>=4.0,<5.0)
Requires-Dist: click (>=8.1,<9.0)
Requires-Dist: dynaconf (>=3.1,<4.0)
Requires-Dist: numpy (>=1.24,<2.0)
Project-URL: Bug Tracker, https://github.com/JDArmy/TextWatermark/issues
Project-URL: Changelog, https://textwatermark.jd.army/changelog/
Project-URL: Documentation, https://textwatermark.jd.army/
Project-URL: Repository, https://github.com/JDArmy/TextWatermark
